bayesoptimize-1.0.1.data/data/LICENSE.txt
optimize/.DS_Store
optimize/__init__.py
optimize/data.py
optimize/frameworks.py
optimize/kernels.py
optimize/knowledge.py
optimize/models.py
optimize/neldermead.py
optimize/optimizers.py
optimize/samplers.py
optimize/scipy_optimizers.py
optimize/score.py
optimize/scores.py
optimize/__pycache__/__init__.cpython-38.pyc
optimize/__pycache__/data.cpython-38.pyc
optimize/__pycache__/frameworks.cpython-38.pyc
optimize/__pycache__/kernels.cpython-38.pyc
optimize/__pycache__/knowledge.cpython-38.pyc
optimize/__pycache__/models.cpython-38.pyc
optimize/__pycache__/neldermead.cpython-37.pyc
optimize/__pycache__/neldermead.cpython-38.pyc
optimize/__pycache__/optimizers.cpython-38.pyc
optimize/__pycache__/samplers.cpython-38.pyc
optimize/__pycache__/scipy_optimizers.cpython-38.pyc
optimize/__pycache__/score.cpython-38.pyc
optimize/__pycache__/scores.cpython-38.pyc
bayesoptimize-1.0.1.dist-info/LICENSE.txt
bayesoptimize-1.0.1.dist-info/METADATA
bayesoptimize-1.0.1.dist-info/WHEEL
bayesoptimize-1.0.1.dist-info/top_level.txt
bayesoptimize-1.0.1.dist-info/RECORD
